pubmed_fetcher/__init__.py
pubmed_fetcher/fetcher.py
paperfetch-0.1.0.dist-info/entry_points.txt
paperfetch-0.1.0.dist-info/METADATA
paperfetch-0.1.0.dist-info/WHEEL
paperfetch-0.1.0.dist-info/RECORD
