Metadata-Version: 2.3
Name: paperfetch
Version: 0.1.0
Summary: Python script to fetch research papers from PubMed API and save as CSV.
Author: RasiJeon
Author-email: rasijeon@gmail.com
Requires-Python: >=3.13
Classifier: Programming Language :: Python :: 3
Classifier: Programming Language :: Python :: 3.13
Requires-Dist: pandas (>=2.2.3,<3.0.0)
Requires-Dist: requests (>=2.32.3,<3.0.0)
